rfw_lightning/__init__.py
rfw_lightning-0.0.1.dist-info/WHEEL
rfw_lightning-0.0.1.dist-info/METADATA
rfw_lightning-0.0.1.dist-info/RECORD
