Metadata-Version: 2.1
Name: rfw-lightning
Version: 0.0.1
Summary: Robot Framework Lightning
License: Apache-2.0
Author: RPA Framework
Author-email: rpafw@robocorp.com
Requires-Python: >=3.7.1,<4.0.0
Classifier: License :: OSI Approved :: Apache Software License
Classifier: Programming Language :: Python :: 3
Classifier: Programming Language :: Python :: 3.8
Classifier: Programming Language :: Python :: 3.9
Classifier: Programming Language :: Python :: 3.10
